<?xml version="1.0" encoding="UTF-8"?>
<mappings xmlns="http://dozer.sourceforge.net"
          xmlns:xsi="http://www.w3.org/2001/XMLSchema-instance"
          xsi:schemaLocation="http://dozer.sourceforge.net
          http://dozer.sourceforge.net/schema/beanmapping.xsd">
	
	<mapping>
		<class-a>org.openiam.am.srvc.domain.AuthAttributeEntity</class-a>
		<class-b>org.openiam.am.srvc.domain.AuthAttributeEntity</class-b>
	</mapping>

    <mapping>
        <class-a>org.openiam.idm.srvc.mngsys.domain.ManagedSysEntity</class-a>
        <class-b>org.openiam.idm.srvc.mngsys.domain.ManagedSysEntity</class-b>
    </mapping>
    <mapping>
        <class-a>org.openiam.idm.srvc.mngsys.domain.ManagedSystemObjectMatchEntity</class-a>
        <class-b>org.openiam.idm.srvc.mngsys.domain.ManagedSystemObjectMatchEntity</class-b>
    </mapping>

    <mapping>
        <class-a>org.openiam.am.srvc.domain.AuthLevelEntity</class-a>
        <class-b>org.openiam.am.srvc.domain.AuthLevelEntity</class-b>
    </mapping>

    <mapping>
        <class-a>org.openiam.am.srvc.domain.URIPatternMetaTypeEntity</class-a>
        <class-b>org.openiam.am.srvc.domain.URIPatternMetaTypeEntity</class-b>
    </mapping>

</mappings>